Package/SubPackage/__init__.py
Package/SubPackage/calculator.py
Package/Test/__init__.py
Package/Test/test_code.py
TestSimpleCalculatorEtienneEngel-0.0.2.dist-info/LICENSE.txt
TestSimpleCalculatorEtienneEngel-0.0.2.dist-info/METADATA
TestSimpleCalculatorEtienneEngel-0.0.2.dist-info/WHEEL
TestSimpleCalculatorEtienneEngel-0.0.2.dist-info/top_level.txt
TestSimpleCalculatorEtienneEngel-0.0.2.dist-info/RECORD
