Metadata-Version: 2.1
Name: TestSimpleCalculatorEtienneEngel
Version: 0.0.2
Summary: TestSimpleCalculator is a simple package     in order to make some test on packaging principles in Python
Home-page: UNKNOWN
Author: Etienne Engel
License: GNU GPLv3
Platform: UNKNOWN
Requires-Python: >=3.4
